.DS_Store
jive/AJIVE.py
jive/PCA.py
jive/__init__.py
jive/ajive_fig2.py
jive/random_direction.py
jive/utils.py
jive/wedin_bound.py
jive/lazymatpy/__init__.py
jive/lazymatpy/convert2scipy.py
jive/lazymatpy/interface.py
jive/lazymatpy/templates/__init__.py
jive/lazymatpy/templates/matrix_transformations.py
jive/lazymatpy/templates/ones.py
jive/lazymatpy/templates/tests/__init__.py
jive/lazymatpy/templates/tests/help_fun.py
jive/lazymatpy/templates/tests/test_Ones.py
jive/lazymatpy/templates/tests/test_matrix_transformations.py
jive/lazymatpy/tests/__init__.py
jive/lazymatpy/tests/test_interface.py
jive/tests/__init__.py
jive/tests/test_AJIVE.py
jive/tests/test_PCA.py
jive/tests/utils.py
jive/viz/__init__.py
jive/viz/block_visualization.py
jive/viz/diagnostic_plot.py
jive/viz/jive_visualization.py
jive/viz/pca_scores_plot.py
jive/viz/scatter_plot_save_selected.py
jive/viz/singular_values.py
jive/viz/viz.py
jive-0.2.1.dist-info/LICENSE.txt
jive-0.2.1.dist-info/METADATA
jive-0.2.1.dist-info/WHEEL
jive-0.2.1.dist-info/top_level.txt
jive-0.2.1.dist-info/RECORD
