Metadata-Version: 2.1
Name: jive
Version: 0.2.1
Summary: A data analysis package for high-dimensional, multi-block (multi-view) data.
Home-page: https://github.com/idc9/py_jive
Author: Iain Carmichael
Author-email: idc9@cornell.edu
License: MIT
Platform: UNKNOWN
Classifier: License :: OSI Approved :: MIT License
Classifier: Programming Language :: Python
Classifier: Programming Language :: Python :: 3
Classifier: Programming Language :: Python :: 3.6
Classifier: Programming Language :: Python :: Implementation :: PyPy
Classifier: Intended Audience :: Science/Research
Requires-Python: >=3.6.0
Requires-Dist: numpy
Requires-Dist: scipy
Requires-Dist: pandas
Requires-Dist: seaborn
Requires-Dist: matplotlib
Requires-Dist: scikit-learn
Requires-Dist: statsmodels
Requires-Dist: joblib
Requires-Dist: bokeh
